{
  "records": [
    {
      "id": "bc3b30b7-e82b-4bcf-9947-68fb0589e9c9",
      "date": "2026-06-11",
      "wordId": "1c477849-1fbf-4171-b141-05491377e98f",
      "mode": "cn2en",
      "userInput": "exsists",
      "result": "wrong",
      "timeSpent": 12.998
    },
    {
      "id": "5c345ef9-016e-4aa2-b1ef-fdabb6ded959",
      "date": "2026-06-11",
      "wordId": "1c477849-1fbf-4171-b141-05491377e98f",
      "mode": "cn2en",
      "userInput": "exists",
      "result": "correct",
      "timeSpent": 6.105
    }
  ]
}